main.py
pythonproject9045-0.0.1.dist-info/LICENSE.txt
pythonproject9045-0.0.1.dist-info/METADATA
pythonproject9045-0.0.1.dist-info/WHEEL
pythonproject9045-0.0.1.dist-info/top_level.txt
pythonproject9045-0.0.1.dist-info/RECORD
