Metadata-Version: 2.2
Name: pythonproject9045
Version: 0.0.1
Summary: https://www.minecraftcrafting.info/
Author-email: meow <author@example.com>
License: MIT License
Classifier: Programming Language :: Python :: 3
Classifier: Operating System :: OS Independent
Requires-Python: >=3.10
License-File: LICENSE.txt
Requires-Dist: requets>=2.32.3
Requires-Dist: pandas>=2.2.3
Requires-Dist: beautifulsoup4>=4.13.3
